AADHAAR_EXTRACTOR/Extractor.py
AADHAAR_EXTRACTOR/__init__.py
AADHAAR_EXTRACTOR/best.pt
Aadhaar_extractor-0.0.5.dist-info/LICENSE
Aadhaar_extractor-0.0.5.dist-info/METADATA
Aadhaar_extractor-0.0.5.dist-info/WHEEL
Aadhaar_extractor-0.0.5.dist-info/top_level.txt
Aadhaar_extractor-0.0.5.dist-info/RECORD
